{
    "2026-06-13": {
        "normal": {
            "kanji": "陣場駅",
            "yomi": "じんば",
            "pref": "秋田県",
            "municipality": "大館市"
        },
        "hard": {
            "kanji": "落居駅",
            "yomi": "おちい",
            "pref": "山梨県",
            "municipality": "市川三郷町"
        }
    },
    "2026-06-14": {
        "normal": {
            "kanji": "桟橋通三丁目停留場",
            "yomi": "さんばしどおりさんちょうめ",
            "pref": "高知県",
            "municipality": "高知市"
        },
        "hard": {
            "kanji": "柳津駅 (宮城県)",
            "yomi": "やないづ",
            "pref": "宮城県",
            "municipality": "登米市"
        }
    },
    "2026-06-15": {
        "normal": {
            "kanji": "柳本駅",
            "yomi": "やなぎもと",
            "pref": "奈良県",
            "municipality": "天理市"
        },
        "hard": {
            "kanji": "井高野駅",
            "yomi": "いたかの",
            "pref": "大阪府",
            "municipality": "大阪市"
        }
    },
    "2026-06-16": {
        "normal": {
            "kanji": "床波駅",
            "yomi": "とこなみ",
            "pref": "山口県",
            "municipality": "宇部市"
        },
        "hard": {
            "kanji": "鵜殿駅",
            "yomi": "うどの",
            "pref": "三重県",
            "municipality": "紀宝町"
        }
    },
    "2026-06-17": {
        "normal": {
            "kanji": "道ノ尾駅",
            "yomi": "みちのお",
            "pref": "長崎県",
            "municipality": "長崎市"
        },
        "hard": {
            "kanji": "新検見川駅",
            "yomi": "しんけみがわ",
            "pref": "千葉県",
            "municipality": "千葉市"
        }
    },
    "2026-06-18": {
        "normal": {
            "kanji": "北池野駅",
            "yomi": "きたいけの",
            "pref": "岐阜県",
            "municipality": "池田町"
        },
        "hard": {
            "kanji": "船橋日大前駅",
            "yomi": "ふなばしにちだいまえ",
            "pref": "千葉県",
            "municipality": "船橋市"
        }
    },
    "2026-06-19": {
        "normal": {
            "kanji": "湯田温泉駅",
            "yomi": "ゆだおんせん",
            "pref": "山口県",
            "municipality": "山口市"
        },
        "hard": {
            "kanji": "青笹駅",
            "yomi": "あおざさ",
            "pref": "岩手県",
            "municipality": "遠野市"
        }
    },
    "2026-06-20": {
        "normal": {
            "kanji": "湯田温泉駅",
            "yomi": "ゆだおんせん",
            "pref": "山口県",
            "municipality": "山口市"
        },
        "hard": {
            "kanji": "木ノ本駅",
            "yomi": "きのもと",
            "pref": "滋賀県",
            "municipality": "長浜市"
        }
    },
    "2026-06-21": {
        "normal": {
            "kanji": "香呂駅",
            "yomi": "こうろ",
            "pref": "兵庫県",
            "municipality": "姫路市"
        },
        "hard": {
            "kanji": "茂辺地駅",
            "yomi": "もへじ",
            "pref": "北海道",
            "municipality": "北斗市"
        }
    },
    "2026-06-22": {
        "normal": {
            "kanji": "東別院駅",
            "yomi": "ひがしべついん",
            "pref": "愛知県",
            "municipality": "名古屋市"
        },
        "hard": {
            "kanji": "樟葉駅",
            "yomi": "くずは",
            "pref": "大阪府",
            "municipality": "枚方市"
        }
    },
    "2026-06-23": {
        "normal": {
            "kanji": "日本橋駅 (東京都)",
            "yomi": "にほんばし",
            "pref": "東京都",
            "municipality": "中央区"
        },
        "hard": {
            "kanji": "所沢駅",
            "yomi": "ところざわ",
            "pref": "埼玉県",
            "municipality": "所沢市"
        }
    },
    "2026-06-24": {
        "normal": {
            "kanji": "三毛門駅",
            "yomi": "みけかど",
            "pref": "福岡県",
            "municipality": "豊前市"
        },
        "hard": {
            "kanji": "服部駅",
            "yomi": "はっとり",
            "pref": "岡山県",
            "municipality": "総社市"
        }
    },
    "2026-06-25": {
        "normal": {
            "kanji": "宮ケ浜駅",
            "yomi": "みやがはま",
            "pref": "鹿児島県",
            "municipality": "指宿市"
        },
        "hard": {
            "kanji": "相内駅",
            "yomi": "あいのない",
            "pref": "北海道",
            "municipality": "北見市"
        }
    },
    "2026-06-26": {
        "normal": {
            "kanji": "佐里駅",
            "yomi": "さり",
            "pref": "佐賀県",
            "municipality": "唐津市"
        },
        "hard": {
            "kanji": "野花南駅",
            "yomi": "のかなん",
            "pref": "北海道",
            "municipality": "芦別市"
        }
    },
    "2026-06-27": {
        "normal": {
            "kanji": "沢尻駅",
            "yomi": "さわじり",
            "pref": "秋田県",
            "municipality": "大館市"
        },
        "hard": {
            "kanji": "西新発田駅",
            "yomi": "にししばた",
            "pref": "新潟県",
            "municipality": "新発田市"
        }
    },
    "2026-06-28": {
        "normal": {
            "kanji": "大関駅",
            "yomi": "おおぜき",
            "pref": "福井県",
            "municipality": "坂井市"
        },
        "hard": {
            "kanji": "今宮戎駅",
            "yomi": "いまみやえびす",
            "pref": "大阪府",
            "municipality": "大阪市"
        }
    },
    "2026-06-29": {
        "normal": {
            "kanji": "笹平駅",
            "yomi": "ささだいら",
            "pref": "富山県",
            "municipality": "黒部市"
        },
        "hard": {
            "kanji": "相武台下駅",
            "yomi": "そうぶだいした",
            "pref": "神奈川県",
            "municipality": "相模原市"
        }
    },
    "2026-06-30": {
        "normal": {
            "kanji": "草野駅 (福島県)",
            "yomi": "くさの",
            "pref": "福島県",
            "municipality": "いわき市"
        },
        "hard": {
            "kanji": "美濃白鳥駅",
            "yomi": "みのしろとり",
            "pref": "岐阜県",
            "municipality": "郡上市"
        }
    },
    "2026-07-01": {
        "normal": {
            "kanji": "鳥ノ木駅",
            "yomi": "とりのき",
            "pref": "愛媛県",
            "municipality": "伊予市"
        },
        "hard": {
            "kanji": "篠ノ井駅",
            "yomi": "しののい",
            "pref": "長野県",
            "municipality": "長野市"
        }
    },
    "2026-07-02": {
        "normal": {
            "kanji": "宝珠山駅",
            "yomi": "ほうしゅやま",
            "pref": "福岡県",
            "municipality": "東峰村"
        },
        "hard": {
            "kanji": "綾部駅",
            "yomi": "あやべ",
            "pref": "京都府",
            "municipality": "綾部市"
        }
    },
    "2026-07-03": {
        "normal": {
            "kanji": "智北駅",
            "yomi": "ちほく",
            "pref": "北海道",
            "municipality": "名寄市"
        },
        "hard": {
            "kanji": "高師駅",
            "yomi": "たかし",
            "pref": "愛知県",
            "municipality": "豊橋市"
        }
    },
    "2026-07-04": {
        "normal": {
            "kanji": "西松井田駅",
            "yomi": "にしまついだ",
            "pref": "群馬県",
            "municipality": "安中市"
        },
        "hard": {
            "kanji": "清流新岩国駅",
            "yomi": "せいりゅうしんいわくに",
            "pref": "山口県",
            "municipality": "岩国市"
        }
    },
    "2026-07-05": {
        "normal": {
            "kanji": "大藪駅",
            "yomi": "おおやぶ",
            "pref": "福岡県",
            "municipality": "田川市"
        },
        "hard": {
            "kanji": "五稜郭駅",
            "yomi": "ごりょうかく",
            "pref": "北海道",
            "municipality": "函館市"
        }
    },
    "2026-07-06": {
        "normal": {
            "kanji": "上浦駅",
            "yomi": "かみうら",
            "pref": "福岡県",
            "municipality": "朝倉市"
        },
        "hard": {
            "kanji": "多賀大社前駅",
            "yomi": "たがたいしゃまえ",
            "pref": "滋賀県",
            "municipality": "多賀町"
        }
    },
    "2026-07-07": {
        "normal": {
            "kanji": "薬師堂駅 (秋田県)",
            "yomi": "やくしどう",
            "pref": "秋田県",
            "municipality": "由利本荘市"
        },
        "hard": {
            "kanji": "紫香楽宮跡駅",
            "yomi": "しがらきぐうし",
            "pref": "滋賀県",
            "municipality": "甲賀市"
        }
    },
    "2026-07-08": {
        "normal": {
            "kanji": "四季の郷駅",
            "yomi": "しきのさと",
            "pref": "山形県",
            "municipality": "白鷹町"
        },
        "hard": {
            "kanji": "下菅谷駅",
            "yomi": "しもすがや",
            "pref": "茨城県",
            "municipality": "那珂市"
        }
    },
    "2026-07-09": {
        "normal": {
            "kanji": "千代田駅",
            "yomi": "ちよだ",
            "pref": "大阪府",
            "municipality": "河内長野市"
        },
        "hard": {
            "kanji": "社町駅",
            "yomi": "やしろちょう",
            "pref": "兵庫県",
            "municipality": "加東市"
        }
    },
    "2026-07-10": {
        "normal": {
            "kanji": "薊野駅",
            "yomi": "あぞうの",
            "pref": "高知県",
            "municipality": "高知市"
        },
        "hard": {
            "kanji": "北府駅",
            "yomi": "きたご",
            "pref": "福井県",
            "municipality": "越前市"
        }
    },
    "2026-07-11": {
        "normal": {
            "kanji": "北藤岡駅",
            "yomi": "きたふじおか",
            "pref": "群馬県",
            "municipality": "藤岡市"
        },
        "hard": {
            "kanji": "伊香牛駅",
            "yomi": "いかうし",
            "pref": "北海道",
            "municipality": "当麻町"
        }
    },
    "2026-07-12": {
        "normal": {
            "kanji": "下深谷駅",
            "yomi": "しもふかや",
            "pref": "三重県",
            "municipality": "桑名市"
        },
        "hard": {
            "kanji": "下川合駅",
            "yomi": "しもかわい",
            "pref": "静岡県",
            "municipality": "浜松市"
        }
    },
    "2026-07-13": {
        "normal": {
            "kanji": "家庭裁判所前停留場",
            "yomi": "かていさいばんしょまえ",
            "pref": "広島県",
            "municipality": "広島市"
        },
        "hard": {
            "kanji": "小路駅",
            "yomi": "しょうじ",
            "pref": "大阪府",
            "municipality": "大阪市"
        }
    },
    "2026-07-14": {
        "normal": {
            "kanji": "平津駅",
            "yomi": "へいづ",
            "pref": "三重県",
            "municipality": "四日市市"
        },
        "hard": {
            "kanji": "駒場東大前駅",
            "yomi": "こまばとうだいまえ",
            "pref": "東京都",
            "municipality": "目黒区"
        }
    },
    "2026-07-15": {
        "normal": {
            "kanji": "石巻あゆみ野駅",
            "yomi": "いしのまきあゆみの",
            "pref": "宮城県",
            "municipality": "石巻市"
        },
        "hard": {
            "kanji": "三岡駅",
            "yomi": "みつおか",
            "pref": "長野県",
            "municipality": "小諸市"
        }
    },
    "2026-07-16": {
        "normal": {
            "kanji": "依那古駅",
            "yomi": "いなこ",
            "pref": "三重県",
            "municipality": "伊賀市"
        },
        "hard": {
            "kanji": "高崎問屋町駅",
            "yomi": "たかさきとんやまち",
            "pref": "群馬県",
            "municipality": "高崎市"
        }
    },
    "2026-07-17": {
        "normal": {
            "kanji": "馬来田駅",
            "yomi": "まくた",
            "pref": "千葉県",
            "municipality": "木更津市"
        },
        "hard": {
            "kanji": "穴部駅",
            "yomi": "あなべ",
            "pref": "神奈川県",
            "municipality": "小田原市"
        }
    },
    "2026-07-18": {
        "normal": {
            "kanji": "足ケ瀬駅",
            "yomi": "あしがせ",
            "pref": "岩手県",
            "municipality": "遠野市"
        },
        "hard": {
            "kanji": "半家駅",
            "yomi": "はげ",
            "pref": "高知県",
            "municipality": "四万十市"
        }
    },
    "2026-07-19": {
        "normal": {
            "kanji": "春日部駅",
            "yomi": "かすかべ",
            "pref": "埼玉県",
            "municipality": "春日部市"
        },
        "hard": {
            "kanji": "神栖駅",
            "yomi": "かみす",
            "pref": "茨城県",
            "municipality": "神栖市"
        }
    },
    "2026-07-20": {
        "normal": {
            "kanji": "滝水駅",
            "yomi": "たきみず",
            "pref": "熊本県",
            "municipality": "阿蘇市"
        },
        "hard": {
            "kanji": "八津駅",
            "yomi": "やつ",
            "pref": "秋田県",
            "municipality": "仙北市"
        }
    },
    "2026-07-21": {
        "normal": {
            "kanji": "戸狩野沢温泉駅",
            "yomi": "とがりのざわおんせん",
            "pref": "長野県",
            "municipality": "飯山市"
        },
        "hard": {
            "kanji": "マリンパーク駅",
            "yomi": "マリンパーク",
            "pref": "兵庫県",
            "municipality": "神戸市"
        }
    },
    "2026-07-22": {
        "normal": {
            "kanji": "風早駅",
            "yomi": "かざはや",
            "pref": "広島県",
            "municipality": "東広島市"
        },
        "hard": {
            "kanji": "鎌取駅",
            "yomi": "かまとり",
            "pref": "千葉県",
            "municipality": "千葉市"
        }
    },
    "2026-07-23": {
        "normal": {
            "kanji": "博多南駅",
            "yomi": "はかたみなみ",
            "pref": "福岡県",
            "municipality": "春日市"
        },
        "hard": {
            "kanji": "豊後豊岡駅",
            "yomi": "ぶんごとよおか",
            "pref": "大分県",
            "municipality": "日出町"
        }
    },
    "2026-07-24": {
        "normal": {
            "kanji": "紀伊日置駅",
            "yomi": "きいひき",
            "pref": "和歌山県",
            "municipality": "白浜町"
        },
        "hard": {
            "kanji": "ケーブル八幡宮口駅",
            "yomi": "ケーブルはちまんぐうぐち",
            "pref": "京都府",
            "municipality": "八幡市"
        }
    },
    "2026-07-25": {
        "normal": {
            "kanji": "志村三丁目駅",
            "yomi": "しむらさんちょうめ",
            "pref": "東京都",
            "municipality": "板橋区"
        },
        "hard": {
            "kanji": "十勝清水駅",
            "yomi": "とかちしみず",
            "pref": "北海道",
            "municipality": "清水町"
        }
    },
    "2026-07-26": {
        "normal": {
            "kanji": "新発田駅",
            "yomi": "しばた",
            "pref": "新潟県",
            "municipality": "新発田市"
        },
        "hard": {
            "kanji": "茂吉記念館前駅",
            "yomi": "もきちきねんかんまえ",
            "pref": "山形県",
            "municipality": "上山市"
        }
    },
    "2026-07-27": {
        "normal": {
            "kanji": "新庚申塚停留場",
            "yomi": "しんこうしんづか",
            "pref": "東京都",
            "municipality": "豊島区"
        },
        "hard": {
            "kanji": "美山駅",
            "yomi": "みやま",
            "pref": "福井県",
            "municipality": "福井市"
        }
    },
    "2026-07-28": {
        "normal": {
            "kanji": "南郷18丁目駅",
            "yomi": "なんごうじゅうはっちょうめ",
            "pref": "北海道",
            "municipality": "札幌市"
        },
        "hard": {
            "kanji": "武並駅",
            "yomi": "たけなみ",
            "pref": "岐阜県",
            "municipality": "恵那市"
        }
    }
}